textarium/.DS_Store
textarium/__init__.py
textarium/collections/__init__.py
textarium/collections/en_stopwords.txt
textarium/collections/ru_stopwords.txt
textarium/collections/stopwords.py
textarium/corpus.py
textarium/extraction.py
textarium/models.py
textarium/preprocessing.py
textarium/stats/__init__.py
textarium/stats/text_stats.py
textarium/termdoc.py
textarium/tests/__init__.py
textarium/tests/test__all__.py
textarium/tests/test_collections.py
textarium/tests/test_corpus.py
textarium/tests/test_extraction.py
textarium/tests/test_preprocessing.py
textarium/tests/test_text.py
textarium/tests/test_text_stats.py
textarium/text.py
textarium/utils.py
textarium-0.1.9.dist-info/LICENSE
textarium-0.1.9.dist-info/METADATA
textarium-0.1.9.dist-info/WHEEL
textarium-0.1.9.dist-info/RECORD
