Metadata-Version: 2.1
Name: textarium
Version: 0.1.9
Summary: Textarium is a Python package for text analysis
License: MIT
Author: 6b656b
Requires-Python: >=3.9,<4.0
Classifier: License :: OSI Approved :: MIT License
Classifier: Programming Language :: Python :: 3
Classifier: Programming Language :: Python :: 3.9
Classifier: Programming Language :: Python :: 3.10
Classifier: Programming Language :: Python :: 3.11
Requires-Dist: nltk (>=3.8.1,<4.0.0)
Requires-Dist: prettytable (>=3.9.0,<4.0.0)
Requires-Dist: pymorphy2 (>=0.9.1,<0.10.0)
Requires-Dist: pymorphy2-dicts (>=2.4.393442.3710985,<3.0.0.0)
Requires-Dist: pytest (>=7.1.3,<8.0.0)
Requires-Dist: python-dateutil (>=2.8.2,<3.0.0)
Requires-Dist: razdel (>=0.5.0,<0.6.0)
Requires-Dist: scikit-learn (>=1.3.1,<2.0.0)
Requires-Dist: setuptools (>=65.6.3,<66.0.0)
Requires-Dist: toml (>=0.10.2,<0.11.0)
Requires-Dist: yake (>=0.4.8,<0.5.0)
